buildout.cfg
setup.py
src/zc/__init__.py
src/zc/parse_addr.py
src/zc.parse_addr.egg-info/PKG-INFO
src/zc.parse_addr.egg-info/SOURCES.txt
src/zc.parse_addr.egg-info/dependency_links.txt
src/zc.parse_addr.egg-info/namespace_packages.txt
src/zc.parse_addr.egg-info/not-zip-safe
src/zc.parse_addr.egg-info/requires.txt
src/zc.parse_addr.egg-info/top_level.txt