Metadata-Version: 1.0
Name: zc.parse-addr
Version: 1.0.0
Summary: Parse network addresses of the form: HOST:PORT
Home-page: UNKNOWN
Author: Jim Fulton
Author-email: jim@zope.com
License: ZPL 2.1
Platform: UNKNOWN
